{
	"selection": [
		{
			"name": "angle-double-down",
			"order": 0,
			"prevSize": 28
		},
		{
			"name": "angle-double-left",
			"order": 0,
			"prevSize": 28
		},
		{
			"name": "angle-double-right",
			"order": 0,
			"prevSize": 28
		},
		{
			"name": "angle-double-up",
			"order": 0,
			"prevSize": 28
		},
		{
			"name": "angle-down",
			"order": 0,
			"prevSize": 28
		},
		{
			"name": "angle-left",
			"order": 0,
			"prevSize": 28
		},
		{
			"name": "angle-right",
			"order": 0,
			"prevSize": 28
		},
		{
			"name": "angle-up",
			"order": 0,
			"prevSize": 28
		},
		{
			"name": "arrow-circle-down",
			"order": 0,
			"prevSize": 28
		},
		{
			"name": "arrow-circle-left",
			"order": 0,
			"prevSize": 28
		},
		{
			"name": "arrow-circle-o-down",
			"order": 0,
			"prevSize": 28
		},
		{
			"name": "arrow-circle-o-left",
			"order": 0,
			"prevSize": 28
		},
		{
			"name": "arrow-circle-o-right",
			"order": 0,
			"prevSize": 28
		},
		{
			"name": "arrow-circle-o-up",
			"order": 0,
			"prevSize": 28
		},
		{
			"name": "arrow-circle-right",
			"order": 0,
			"prevSize": 28
		},
		{
			"name": "arrow-circle-up",
			"order": 0,
			"prevSize": 28
		},
		{
			"name": "arrow-down",
			"order": 0,
			"prevSize": 28
		},
		{
			"name": "arrow-left",
			"order": 0,
			"prevSize": 28
		},
		{
			"name": "arrow-right",
			"order": 0,
			"prevSize": 28
		},
		{
			"name": "arrow-up",
			"order": 0,
			"prevSize": 28
		},
		{
			"name": "arrows",
			"order": 0,
			"prevSize": 28
		},
		{
			"name": "arrows-alt",
			"order": 0,
			"prevSize": 28
		},
		{
			"name": "arrows-h",
			"order": 0,
			"prevSize": 28
		},
		{
			"name": "arrows-v",
			"order": 0,
			"prevSize": 28
		},
		{
			"name": "caret-down",
			"order": 0,
			"prevSize": 28
		},
		{
			"name": "caret-left",
			"order": 0,
			"prevSize": 28
		},
		{
			"name": "caret-right",
			"order": 0,
			"prevSize": 28
		},
		{
			"name": "caret-square-o-down, toggle-down",
			"order": 0,
			"prevSize": 28
		},
		{
			"name": "caret-square-o-left, toggle-left",
			"order": 0,
			"prevSize": 28
		},
		{
			"name": "caret-square-o-right, toggle-right",
			"order": 0,
			"prevSize": 28
		},
		{
			"name": "caret-square-o-up, toggle-up",
			"order": 0,
			"prevSize": 28
		},
		{
			"name": "caret-up",
			"order": 0,
			"prevSize": 28
		},
		{
			"name": "chevron-circle-down",
			"order": 0,
			"prevSize": 28
		},
		{
			"name": "chevron-circle-left",
			"order": 0,
			"prevSize": 28
		},
		{
			"name": "chevron-circle-right",
			"order": 0,
			"prevSize": 28
		},
		{
			"name": "chevron-circle-up",
			"order": 0,
			"prevSize": 28
		},
		{
			"name": "chevron-down",
			"order": 0,
			"prevSize": 28
		},
		{
			"name": "chevron-left",
			"order": 0,
			"prevSize": 28
		},
		{
			"name": "chevron-right",
			"order": 0,
			"prevSize": 28
		},
		{
			"name": "chevron-up",
			"order": 0,
			"prevSize": 28
		},
		{
			"name": "cloud-download",
			"order": 0,
			"prevSize": 28
		},
		{
			"name": "cloud-upload",
			"order": 0,
			"prevSize": 28
		},
		{
			"name": "compress",
			"order": 0,
			"prevSize": 28
		},
		{
			"name": "download",
			"order": 0,
			"prevSize": 28
		},
		{
			"name": "exchange",
			"order": 0,
			"prevSize": 28
		},
		{
			"name": "expand",
			"order": 0,
			"prevSize": 28
		},
		{
			"name": "hand-o-down",
			"order": 0,
			"prevSize": 28
		},
		{
			"name": "hand-o-left",
			"order": 0,
			"prevSize": 28
		},
		{
			"name": "hand-o-right",
			"order": 0,
			"prevSize": 28
		},
		{
			"name": "hand-o-up",
			"order": 0,
			"prevSize": 28
		},
		{
			"name": "history",
			"order": 0,
			"prevSize": 28
		},
		{
			"name": "level-down",
			"order": 0,
			"prevSize": 28
		},
		{
			"name": "level-up",
			"order": 0,
			"prevSize": 28
		},
		{
			"name": "long-arrow-down",
			"order": 0,
			"prevSize": 28
		},
		{
			"name": "long-arrow-left",
			"order": 0,
			"prevSize": 28
		},
		{
			"name": "long-arrow-right",
			"order": 0,
			"prevSize": 28
		},
		{
			"name": "long-arrow-up",
			"order": 0,
			"prevSize": 28
		},
		{
			"name": "mail-forward, share",
			"order": 0,
			"prevSize": 28
		},
		{
			"name": "mail-reply, reply",
			"order": 0,
			"prevSize": 28
		},
		{
			"name": "mail-reply-all, reply-all",
			"order": 0,
			"prevSize": 28
		},
		{
			"name": "random",
			"order": 0,
			"prevSize": 28
		},
		{
			"name": "refresh",
			"order": 0,
			"prevSize": 28
		},
		{
			"name": "repeat, rotate-right",
			"order": 0,
			"prevSize": 28
		},
		{
			"name": "retweet",
			"order": 0,
			"prevSize": 28
		},
		{
			"name": "rotate-left, undo",
			"order": 0,
			"prevSize": 28
		},
		{
			"name": "share-square",
			"order": 0,
			"prevSize": 28
		},
		{
			"name": "share-square-o",
			"order": 0,
			"prevSize": 28
		},
		{
			"name": "sign-in",
			"order": 0,
			"prevSize": 28
		},
		{
			"name": "sign-out",
			"order": 0,
			"prevSize": 28
		},
		{
			"name": "sort, unsorted",
			"order": 0,
			"prevSize": 28
		},
		{
			"name": "sort-asc, sort-up",
			"order": 0,
			"prevSize": 28
		},
		{
			"name": "sort-desc, sort-down",
			"order": 0,
			"prevSize": 28
		},
		{
			"name": "upload",
			"order": 0,
			"prevSize": 28
		}
	],
	"metadata": {
		"name": "Font Awesome 4.6.1 – Arrows, etc.",
		"url": "http://fortawesome.github.com/Font-Awesome/",
		"designer": "Dave Gandy",
		"designerURL": "https://github.com/davegandy",
		"license": "Custom",
		"licenseURL": "http://fortawesome.github.io/Font-Awesome/license/",
		"iconsHash": 1691777564
	},
	"height": 1024,
	"prevSize": 28,
	"icons": [
		{
			"paths": [
				"M614.286 493.714q0 7.429-5.714 13.143l-266.286 266.286q-5.714 5.714-13.143 5.714t-13.143-5.714l-266.286-266.286q-5.714-5.714-5.714-13.143t5.714-13.143l28.571-28.571q5.714-5.714 13.143-5.714t13.143 5.714l224.571 224.571 224.571-224.571q5.714-5.714 13.143-5.714t13.143 5.714l28.571 28.571q5.714 5.714 5.714 13.143zM614.286 274.286q0 7.429-5.714 13.143l-266.286 266.286q-5.714 5.714-13.143 5.714t-13.143-5.714l-266.286-266.286q-5.714-5.714-5.714-13.143t5.714-13.143l28.571-28.571q5.714-5.714 13.143-5.714t13.143 5.714l224.571 224.571 224.571-224.571q5.714-5.714 13.143-5.714t13.143 5.714l28.571 28.571q5.714 5.714 5.714 13.143z"
			],
			"width": 658.2859878540039,
			"tags": [
				"angle-double-down"
			],
			"defaultCode": 61699,
			"grid": 14
		},
		{
			"paths": [
				"M358.286 786.286q0 7.429-5.714 13.143l-28.571 28.571q-5.714 5.714-13.143 5.714t-13.143-5.714l-266.286-266.286q-5.714-5.714-5.714-13.143t5.714-13.143l266.286-266.286q5.714-5.714 13.143-5.714t13.143 5.714l28.571 28.571q5.714 5.714 5.714 13.143t-5.714 13.143l-224.571 224.571 224.571 224.571q5.714 5.714 5.714 13.143zM577.714 786.286q0 7.429-5.714 13.143l-28.571 28.571q-5.714 5.714-13.143 5.714t-13.143-5.714l-266.286-266.286q-5.714-5.714-5.714-13.143t5.714-13.143l266.286-266.286q5.714-5.714 13.143-5.714t13.143 5.714l28.571 28.571q5.714 5.714 5.714 13.143t-5.714 13.143l-224.571 224.571 224.571 224.571q5.714 5.714 5.714 13.143z"
			],
			"width": 603.4289932250977,
			"tags": [
				"angle-double-left"
			],
			"defaultCode": 61696,
			"grid": 14
		},
		{
			"paths": [
				"M340 548.571q0 7.429-5.714 13.143l-266.286 266.286q-5.714 5.714-13.143 5.714t-13.143-5.714l-28.571-28.571q-5.714-5.714-5.714-13.143t5.714-13.143l224.571-224.571-224.571-224.571q-5.714-5.714-5.714-13.143t5.714-13.143l28.571-28.571q5.714-5.714 13.143-5.714t13.143 5.714l266.286 266.286q5.714 5.714 5.714 13.143zM559.429 548.571q0 7.429-5.714 13.143l-266.286 266.286q-5.714 5.714-13.143 5.714t-13.143-5.714l-28.571-28.571q-5.714-5.714-5.714-13.143t5.714-13.143l224.571-224.571-224.571-224.571q-5.714-5.714-5.714-13.143t5.714-13.143l28.571-28.571q5.714-5.714 13.143-5.714t13.143 5.714l266.286 266.286q5.714 5.714 5.714 13.143z"
			],
			"width": 566.8580112457275,
			"tags": [
				"angle-double-right"
			],
			"defaultCode": 61697,
			"grid": 14
		},
		{
			"paths": [
				"M614.286 749.714q0 7.429-5.714 13.143l-28.571 28.571q-5.714 5.714-13.143 5.714t-13.143-5.714l-224.571-224.571-224.571 224.571q-5.714 5.714-13.143 5.714t-13.143-5.714l-28.571-28.571q-5.714-5.714-5.714-13.143t5.714-13.143l266.286-266.286q5.714-5.714 13.143-5.714t13.143 5.714l266.286 266.286q5.714 5.714 5.714 13.143zM614.286 530.286q0 7.429-5.714 13.143l-28.571 28.571q-5.714 5.714-13.143 5.714t-13.143-5.714l-224.571-224.571-224.571 224.571q-5.714 5.714-13.143 5.714t-13.143-5.714l-28.571-28.571q-5.714-5.714-5.714-13.143t5.714-13.143l266.286-266.286q5.714-5.714 13.143-5.714t13.143 5.714l266.286 266.286q5.714 5.714 5.714 13.143z"
			],
			"width": 658.2901077270508,
			"tags": [
				"angle-double-up"
			],
			"defaultCode": 61698,
			"grid": 14
		},
		{
			"paths": [
				"M614.286 420.571q0 7.429-5.714 13.143l-266.286 266.286q-5.714 5.714-13.143 5.714t-13.143-5.714l-266.286-266.286q-5.714-5.714-5.714-13.143t5.714-13.143l28.571-28.571q5.714-5.714 13.143-5.714t13.143 5.714l224.571 224.571 224.571-224.571q5.714-5.714 13.143-5.714t13.143 5.714l28.571 28.571q5.714 5.714 5.714 13.143z"
			],
			"width": 658.2859878540039,
			"tags": [
				"angle-down"
			],
			"defaultCode": 61703,
			"grid": 14
		},
		{
			"paths": [
				"M358.286 310.857q0 7.429-5.714 13.143l-224.571 224.571 224.571 224.571q5.714 5.714 5.714 13.143t-5.714 13.143l-28.571 28.571q-5.714 5.714-13.143 5.714t-13.143-5.714l-266.286-266.286q-5.714-5.714-5.714-13.143t5.714-13.143l266.286-266.286q5.714-5.714 13.143-5.714t13.143 5.714l28.571 28.571q5.714 5.714 5.714 13.143z"
			],
			"width": 384.00101470947266,
			"tags": [
				"angle-left"
			],
			"defaultCode": 61700,
			"grid": 14
		},
		{
			"paths": [
				"M340 548.571q0 7.429-5.714 13.143l-266.286 266.286q-5.714 5.714-13.143 5.714t-13.143-5.714l-28.571-28.571q-5.714-5.714-5.714-13.143t5.714-13.143l224.571-224.571-224.571-224.571q-5.714-5.714-5.714-13.143t5.714-13.143l28.571-28.571q5.714-5.714 13.143-5.714t13.143 5.714l266.286 266.286q5.714 5.714 5.714 13.143z"
			],
			"width": 347.4289951324463,
			"tags": [
				"angle-right"
			],
			"defaultCode": 61701,
			"grid": 14
		},
		{
			"paths": [
				"M614.286 676.571q0 7.429-5.714 13.143l-28.571 28.571q-5.714 5.714-13.143 5.714t-13.143-5.714l-224.571-224.571-224.571 224.571q-5.714 5.714-13.143 5.714t-13.143-5.714l-28.571-28.571q-5.714-5.714-5.714-13.143t5.714-13.143l266.286-266.286q5.714-5.714 13.143-5.714t13.143 5.714l266.286 266.286q5.714 5.714 5.714 13.143z"
			],
			"width": 658.2901077270508,
			"tags": [
				"angle-up"
			],
			"defaultCode": 61702,
			"grid": 14
		},
		{
			"paths": [
				"M733.714 512.571q0-15.429-10.286-25.714l-52-52q-10.286-10.286-25.714-10.286t-25.714 10.286l-108 108v-286.857q0-14.857-10.857-25.714t-25.714-10.857h-73.143q-14.857 0-25.714 10.857t-10.857 25.714v286.857l-108-108q-10.857-10.857-25.714-10.857t-25.714 10.857l-52 52q-10.286 10.286-10.286 25.714t10.286 25.714l258.857 258.857q10.286 10.286 25.714 10.286t25.714-10.286l258.857-258.857q10.286-10.286 10.286-25.714zM877.714 512q0 119.429-58.857 220.286t-159.714 159.714-220.286 58.857-220.286-58.857-159.714-159.714-58.857-220.286 58.857-220.286 159.714-159.714 220.286-58.857 220.286 58.857 159.714 159.714 58.857 220.286z"
			],
			"width": 877.7139282226562,
			"tags": [
				"arrow-circle-down"
			],
			"defaultCode": 61611,
			"grid": 14
		},
		{
			"paths": [
				"M731.429 548.571v-73.143q0-14.857-10.857-25.714t-25.714-10.857h-286.857l108-108q10.857-10.857 10.857-25.714t-10.857-25.714l-52-52q-10.286-10.286-25.714-10.286t-25.714 10.286l-258.857 258.857q-10.286 10.286-10.286 25.714t10.286 25.714l258.857 258.857q10.286 10.286 25.714 10.286t25.714-10.286l52-52q10.286-10.286 10.286-25.714t-10.286-25.714l-108-108h286.857q14.857 0 25.714-10.857t10.857-25.714zM877.714 512q0 119.429-58.857 220.286t-159.714 159.714-220.286 58.857-220.286-58.857-159.714-159.714-58.857-220.286 58.857-220.286 159.714-159.714 220.286-58.857 220.286 58.857 159.714 159.714 58.857 220.286z"
			],
			"width": 877.7139282226562,
			"tags": [
				"arrow-circle-left"
			],
			"defaultCode": 61608,
			"grid": 14
		},
		{
			"paths": [
				"M640 530.286q0 6.857-5.714 13.714l-182.286 182.286q-6.286 5.143-13.143 5.143t-13.143-5.143l-182.857-182.857q-8.571-9.143-4-20 4.571-11.429 17.143-11.429h109.714v-201.143q0-8 5.143-13.143t13.143-5.143h109.714q8 0 13.143 5.143t5.143 13.143v201.143h109.714q8 0 13.143 5.143t5.143 13.143zM438.857 201.143q-84.571 0-156 41.714t-113.143 113.143-41.714 156 41.714 156 113.143 113.143 156 41.714 156-41.714 113.143-113.143 41.714-156-41.714-156-113.143-113.143-156-41.714zM877.714 512q0 119.429-58.857 220.286t-159.714 159.714-220.286 58.857-220.286-58.857-159.714-159.714-58.857-220.286 58.857-220.286 159.714-159.714 220.286-58.857 220.286 58.857 159.714 159.714 58.857 220.286z"
			],
			"width": 877.7139282226562,
			"tags": [
				"arrow-circle-o-down"
			],
			"defaultCode": 61466,
			"grid": 14
		},
		{
			"paths": [
				"M658.286 457.143v109.714q0 7.429-5.429 12.857t-12.857 5.429h-201.143v109.714q0 8-5.143 13.143t-13.143 5.143q-6.857 0-13.714-5.714l-182.286-182.286q-5.143-5.143-5.143-13.143t5.143-13.143l182.857-182.857q5.143-5.143 13.143-5.143 7.429 0 12.857 5.429t5.429 12.857v109.714h201.143q7.429 0 12.857 5.429t5.429 12.857zM749.714 512q0-84.571-41.714-156t-113.143-113.143-156-41.714-156 41.714-113.143 113.143-41.714 156 41.714 156 113.143 113.143 156 41.714 156-41.714 113.143-113.143 41.714-156zM877.714 512q0 119.429-58.857 220.286t-159.714 159.714-220.286 58.857-220.286-58.857-159.714-159.714-58.857-220.286 58.857-220.286 159.714-159.714 220.286-58.857 220.286 58.857 159.714 159.714 58.857 220.286z"
			],
			"width": 877.7139282226562,
			"tags": [
				"arrow-circle-o-left"
			],
			"defaultCode": 61840,
			"grid": 14
		},
		{
			"paths": [
				"M658.286 512q0 8-5.143 13.143l-182.857 182.857q-5.143 5.143-13.143 5.143-7.429 0-12.857-5.429t-5.429-12.857v-109.714h-201.143q-7.429 0-12.857-5.429t-5.429-12.857v-109.714q0-7.429 5.429-12.857t12.857-5.429h201.143v-109.714q0-8 5.143-13.143t13.143-5.143q6.857 0 13.714 5.714l182.286 182.286q5.143 5.143 5.143 13.143zM749.714 512q0-84.571-41.714-156t-113.143-113.143-156-41.714-156 41.714-113.143 113.143-41.714 156 41.714 156 113.143 113.143 156 41.714 156-41.714 113.143-113.143 41.714-156zM877.714 512q0 119.429-58.857 220.286t-159.714 159.714-220.286 58.857-220.286-58.857-159.714-159.714-58.857-220.286 58.857-220.286 159.714-159.714 220.286-58.857 220.286 58.857 159.714 159.714 58.857 220.286z"
			],
			"width": 877.7139282226562,
			"tags": [
				"arrow-circle-o-right"
			],
			"defaultCode": 61838,
			"grid": 14
		},
		{
			"paths": [
				"M638.857 500.571q-4.571 11.429-17.143 11.429h-109.714v201.143q0 8-5.143 13.143t-13.143 5.143h-109.714q-8 0-13.143-5.143t-5.143-13.143v-201.143h-109.714q-8 0-13.143-5.143t-5.143-13.143q0-6.857 5.714-13.714l182.286-182.286q6.286-5.143 13.143-5.143t13.143 5.143l182.857 182.857q8.571 9.143 4 20zM438.857 201.143q-84.571 0-156 41.714t-113.143 113.143-41.714 156 41.714 156 113.143 113.143 156 41.714 156-41.714 113.143-113.143 41.714-156-41.714-156-113.143-113.143-156-41.714zM877.714 512q0 119.429-58.857 220.286t-159.714 159.714-220.286 58.857-220.286-58.857-159.714-159.714-58.857-220.286 58.857-220.286 159.714-159.714 220.286-58.857 220.286 58.857 159.714 159.714 58.857 220.286z"
			],
			"width": 877.7139282226562,
			"tags": [
				"arrow-circle-o-up"
			],
			"defaultCode": 61467,
			"grid": 14
		},
		{
			"paths": [
				"M734.286 512q0-15.429-10.286-25.714l-258.857-258.857q-10.286-10.286-25.714-10.286t-25.714 10.286l-52 52q-10.286 10.286-10.286 25.714t10.286 25.714l108 108h-286.857q-14.857 0-25.714 10.857t-10.857 25.714v73.143q0 14.857 10.857 25.714t25.714 10.857h286.857l-108 108q-10.857 10.857-10.857 25.714t10.857 25.714l52 52q10.286 10.286 25.714 10.286t25.714-10.286l258.857-258.857q10.286-10.286 10.286-25.714zM877.714 512q0 119.429-58.857 220.286t-159.714 159.714-220.286 58.857-220.286-58.857-159.714-159.714-58.857-220.286 58.857-220.286 159.714-159.714 220.286-58.857 220.286 58.857 159.714 159.714 58.857 220.286z"
			],
			"width": 877.7139282226562,
			"tags": [
				"arrow-circle-right"
			],
			"defaultCode": 61609,
			"grid": 14
		},
		{
			"paths": [
				"M733.714 511.429q0-15.429-10.286-25.714l-258.857-258.857q-10.286-10.286-25.714-10.286t-25.714 10.286l-258.857 258.857q-10.286 10.286-10.286 25.714t10.286 25.714l52 52q10.286 10.286 25.714 10.286t25.714-10.286l108-108v286.857q0 14.857 10.857 25.714t25.714 10.857h73.143q14.857 0 25.714-10.857t10.857-25.714v-286.857l108 108q10.857 10.857 25.714 10.857t25.714-10.857l52-52q10.286-10.286 10.286-25.714zM877.714 512q0 119.429-58.857 220.286t-159.714 159.714-220.286 58.857-220.286-58.857-159.714-159.714-58.857-220.286 58.857-220.286 159.714-159.714 220.286-58.857 220.286 58.857 159.714 159.714 58.857 220.286z"
			],
			"width": 877.7139282226562,
			"tags": [
				"arrow-circle-up"
			],
			"defaultCode": 61610,
			"grid": 14
		},
		{
			"paths": [
				"M920.571 475.429q0 30.286-21.143 51.429l-372 372.571q-22.286 21.143-52 21.143-30.286 0-51.429-21.143l-372-372.571q-21.714-20.571-21.714-51.429 0-30.286 21.714-52l42.286-42.857q22.286-21.143 52-21.143 30.286 0 51.429 21.143l168 168v-402.286q0-29.714 21.714-51.429t51.429-21.714h73.143q29.714 0 51.429 21.714t21.714 51.429v402.286l168-168q21.143-21.143 51.429-21.143 29.714 0 52 21.143l42.857 42.857q21.143 22.286 21.143 52z"
			],
			"width": 950.8569107055664,
			"tags": [
				"arrow-down"
			],
			"defaultCode": 61539,
			"grid": 14
		},
		{
			"paths": [
				"M877.714 512v73.143q0 30.286-18.571 51.714t-48.286 21.429h-402.286l167.429 168q21.714 20.571 21.714 51.429t-21.714 51.429l-42.857 43.429q-21.143 21.143-51.429 21.143-29.714 0-52-21.143l-372-372.571q-21.143-21.143-21.143-51.429 0-29.714 21.143-52l372-371.429q21.714-21.714 52-21.714 29.714 0 51.429 21.714l42.857 42.286q21.714 21.714 21.714 52t-21.714 52l-167.429 167.429h402.286q29.714 0 48.286 21.429t18.571 51.714z"
			],
			"width": 914.2860260009766,
			"tags": [
				"arrow-left"
			],
			"defaultCode": 61536,
			"grid": 14
		},
		{
			"paths": [
				"M841.143 548.571q0 30.857-21.143 52l-372 372q-22.286 21.143-52 21.143-29.143 0-51.429-21.143l-42.857-42.857q-21.714-21.714-21.714-52t21.714-52l167.429-167.429h-402.286q-29.714 0-48.286-21.429t-18.571-51.714v-73.143q0-30.286 18.571-51.714t48.286-21.429h402.286l-167.429-168q-21.714-20.571-21.714-51.429t21.714-51.429l42.857-42.857q21.714-21.714 51.429-21.714 30.286 0 52 21.714l372 372q21.143 20 21.143 51.429z"
			],
			"width": 841.141975402832,
			"tags": [
				"arrow-right"
			],
			"defaultCode": 61537,
			"grid": 14
		},
		{
			"paths": [
				"M920.571 554.857q0 29.143-21.143 51.429l-42.857 42.857q-21.714 21.714-52 21.714-30.857 0-51.429-21.714l-168-167.429v402.286q0 29.714-21.429 48.286t-51.714 18.571h-73.143q-30.286 0-51.714-18.571t-21.429-48.286v-402.286l-168 167.429q-20.571 21.714-51.429 21.714t-51.429-21.714l-42.857-42.857q-21.714-21.714-21.714-51.429 0-30.286 21.714-52l372-372q20-21.143 51.429-21.143 30.857 0 52 21.143l372 372q21.143 22.286 21.143 52z"
			],
			"width": 950.8549499511719,
			"tags": [
				"arrow-up"
			],
			"defaultCode": 61538,
			"grid": 14
		},
		{
			"paths": [
				"M1024 512q0 14.857-10.857 25.714l-146.286 146.286q-10.857 10.857-25.714 10.857t-25.714-10.857-10.857-25.714v-73.143h-219.429v219.429h73.143q14.857 0 25.714 10.857t10.857 25.714-10.857 25.714l-146.286 146.286q-10.857 10.857-25.714 10.857t-25.714-10.857l-146.286-146.286q-10.857-10.857-10.857-25.714t10.857-25.714 25.714-10.857h73.143v-219.429h-219.429v73.143q0 14.857-10.857 25.714t-25.714 10.857-25.714-10.857l-146.286-146.286q-10.857-10.857-10.857-25.714t10.857-25.714l146.286-146.286q10.857-10.857 25.714-10.857t25.714 10.857 10.857 25.714v73.143h219.429v-219.429h-73.143q-14.857 0-25.714-10.857t-10.857-25.714 10.857-25.714l146.286-146.286q10.857-10.857 25.714-10.857t25.714 10.857l146.286 146.286q10.857 10.857 10.857 25.714t-10.857 25.714-25.714 10.857h-73.143v219.429h219.429v-73.143q0-14.857 10.857-25.714t25.714-10.857 25.714 10.857l146.286 146.286q10.857 10.857 10.857 25.714z"
			],
			"width": 1023.9999885559082,
			"tags": [
				"arrows"
			],
			"defaultCode": 61511,
			"grid": 14
		},
		{
			"paths": [
				"M733.143 309.143l-202.857 202.857 202.857 202.857 82.286-82.286q16.571-17.714 40-8 22.286 9.714 22.286 33.714v256q0 14.857-10.857 25.714t-25.714 10.857h-256q-24 0-33.714-22.857-9.714-22.286 8-39.429l82.286-82.286-202.857-202.857-202.857 202.857 82.286 82.286q17.714 17.143 8 39.429-9.714 22.857-33.714 22.857h-256q-14.857 0-25.714-10.857t-10.857-25.714v-256q0-24 22.857-33.714 22.286-9.714 39.429 8l82.286 82.286 202.857-202.857-202.857-202.857-82.286 82.286q-10.857 10.857-25.714 10.857-6.857 0-13.714-2.857-22.857-9.714-22.857-33.714v-256q0-14.857 10.857-25.714t25.714-10.857h256q24 0 33.714 22.857 9.714 22.286-8 39.429l-82.286 82.286 202.857 202.857 202.857-202.857-82.286-82.286q-17.714-17.143-8-39.429 9.714-22.857 33.714-22.857h256q14.857 0 25.714 10.857t10.857 25.714v256q0 24-22.286 33.714-7.429 2.857-14.286 2.857-14.857 0-25.714-10.857z"
			],
			"width": 877.7190818786621,
			"tags": [
				"arrows-alt"
			],
			"defaultCode": 61618,
			"grid": 14
		},
		{
			"paths": [
				"M1024 512q0 14.857-10.857 25.714l-146.286 146.286q-10.857 10.857-25.714 10.857t-25.714-10.857-10.857-25.714v-73.143h-585.143v73.143q0 14.857-10.857 25.714t-25.714 10.857-25.714-10.857l-146.286-146.286q-10.857-10.857-10.857-25.714t10.857-25.714l146.286-146.286q10.857-10.857 25.714-10.857t25.714 10.857 10.857 25.714v73.143h585.143v-73.143q0-14.857 10.857-25.714t25.714-10.857 25.714 10.857l146.286 146.286q10.857 10.857 10.857 25.714z"
			],
			"width": 1024.0009956359863,
			"tags": [
				"arrows-h"
			],
			"defaultCode": 61566,
			"grid": 14
		},
		{
			"paths": [
				"M402.286 182.857q0 14.857-10.857 25.714t-25.714 10.857h-73.143v585.143h73.143q14.857 0 25.714 10.857t10.857 25.714-10.857 25.714l-146.286 146.286q-10.857 10.857-25.714 10.857t-25.714-10.857l-146.286-146.286q-10.857-10.857-10.857-25.714t10.857-25.714 25.714-10.857h73.143v-585.143h-73.143q-14.857 0-25.714-10.857t-10.857-25.714 10.857-25.714l146.286-146.286q10.857-10.857 25.714-10.857t25.714 10.857l146.286 146.286q10.857 10.857 10.857 25.714z"
			],
			"width": 438.85801696777344,
			"tags": [
				"arrows-v"
			],
			"defaultCode": 61565,
			"grid": 14
		},
		{
			"paths": [
				"M585.143 402.286q0 14.857-10.857 25.714l-256 256q-10.857 10.857-25.714 10.857t-25.714-10.857l-256-256q-10.857-10.857-10.857-25.714t10.857-25.714 25.714-10.857h512q14.857 0 25.714 10.857t10.857 25.714z"
			],
			"width": 585.1440315246582,
			"tags": [
				"caret-down"
			],
			"defaultCode": 61655,
			"grid": 14
		},
		{
			"paths": [
				"M365.714 256v512q0 14.857-10.857 25.714t-25.714 10.857-25.714-10.857l-256-256q-10.857-10.857-10.857-25.714t10.857-25.714l256-256q10.857-10.857 25.714-10.857t25.714 10.857 10.857 25.714z"
			],
			"width": 402.28599548339844,
			"tags": [
				"caret-left"
			],
			"defaultCode": 61657,
			"grid": 14
		},
		{
			"paths": [
				"M329.143 512q0 14.857-10.857 25.714l-256 256q-10.857 10.857-25.714 10.857t-25.714-10.857-10.857-25.714v-512q0-14.857 10.857-25.714t25.714-10.857 25.714 10.857l256 256q10.857 10.857 10.857 25.714z"
			],
			"width": 329.1440124511719,
			"tags": [
				"caret-right"
			],
			"defaultCode": 61658,
			"grid": 14
		},
		{
			"paths": [
				"M654.286 385.714q10.286 20-2.857 37.714l-182.857 256q-10.857 15.429-29.714 15.429t-29.714-15.429l-182.857-256q-13.143-17.714-2.857-37.714 9.714-20 32.571-20h365.714q22.857 0 32.571 20zM731.429 786.286v-548.571q0-7.429-5.429-12.857t-12.857-5.429h-548.571q-7.429 0-12.857 5.429t-5.429 12.857v548.571q0 7.429 5.429 12.857t12.857 5.429h548.571q7.429 0 12.857-5.429t5.429-12.857zM877.714 237.714v548.571q0 68-48.286 116.286t-116.286 48.286h-548.571q-68 0-116.286-48.286t-48.286-116.286v-548.571q0-68 48.286-116.286t116.286-48.286h548.571q68 0 116.286 48.286t48.286 116.286z"
			],
			"width": 877.7129821777344,
			"tags": [
				"caret-square-o-down",
				"toggle-down"
			],
			"defaultCode": 61776,
			"grid": 14
		},
		{
			"paths": [
				"M585.143 329.143v365.714q0 14.857-10.857 25.714t-25.714 10.857q-11.429 0-21.143-6.857l-256-182.857q-15.429-10.857-15.429-29.714t15.429-29.714l256-182.857q9.714-6.857 21.143-6.857 14.857 0 25.714 10.857t10.857 25.714zM731.429 786.286v-548.571q0-7.429-5.429-12.857t-12.857-5.429h-548.571q-7.429 0-12.857 5.429t-5.429 12.857v548.571q0 7.429 5.429 12.857t12.857 5.429h548.571q7.429 0 12.857-5.429t5.429-12.857zM877.714 237.714v548.571q0 68-48.286 116.286t-116.286 48.286h-548.571q-68 0-116.286-48.286t-48.286-116.286v-548.571q0-68 48.286-116.286t116.286-48.286h548.571q68 0 116.286 48.286t48.286 116.286z"
			],
			"width": 877.7129821777344,
			"tags": [
				"caret-square-o-left",
				"toggle-left"
			],
			"defaultCode": 61841,
			"grid": 14
		},
		{
			"paths": [
				"M621.714 512q0 18.857-15.429 29.714l-256 182.857q-17.714 13.143-37.714 2.857-20-9.714-20-32.571v-365.714q0-22.857 20-32.571 20-10.286 37.714 2.857l256 182.857q15.429 10.857 15.429 29.714zM731.429 786.286v-548.571q0-8-5.143-13.143t-13.143-5.143h-548.571q-8 0-13.143 5.143t-5.143 13.143v548.571q0 8 5.143 13.143t13.143 5.143h548.571q8 0 13.143-5.143t5.143-13.143zM877.714 237.714v548.571q0 68-48.286 116.286t-116.286 48.286h-548.571q-68 0-116.286-48.286t-48.286-116.286v-548.571q0-68 48.286-116.286t116.286-48.286h548.571q68 0 116.286 48.286t48.286 116.286z"
			],
			"width": 877.7129821777344,
			"tags": [
				"caret-square-o-right",
				"toggle-right"
			],
			"defaultCode": 61778,
			"grid": 14
		},
		{
			"paths": [
				"M654.286 638.286q-9.714 20-32.571 20h-365.714q-22.857 0-32.571-20-10.286-20 2.857-37.714l182.857-256q10.857-15.429 29.714-15.429t29.714 15.429l182.857 256q13.143 17.714 2.857 37.714zM731.429 786.286v-548.571q0-7.429-5.429-12.857t-12.857-5.429h-548.571q-7.429 0-12.857 5.429t-5.429 12.857v548.571q0 7.429 5.429 12.857t12.857 5.429h548.571q7.429 0 12.857-5.429t5.429-12.857zM877.714 237.714v548.571q0 68-48.286 116.286t-116.286 48.286h-548.571q-68 0-116.286-48.286t-48.286-116.286v-548.571q0-68 48.286-116.286t116.286-48.286h548.571q68 0 116.286 48.286t48.286 116.286z"
			],
			"width": 877.7129821777344,
			"tags": [
				"caret-square-o-up",
				"toggle-up"
			],
			"defaultCode": 61777,
			"grid": 14
		},
		{
			"paths": [
				"M585.143 694.857q0 14.857-10.857 25.714t-25.714 10.857h-512q-14.857 0-25.714-10.857t-10.857-25.714 10.857-25.714l256-256q10.857-10.857 25.714-10.857t25.714 10.857l256 256q10.857 10.857 10.857 25.714z"
			],
			"width": 585.1440086364746,
			"tags": [
				"caret-up"
			],
			"defaultCode": 61656,
			"grid": 14
		},
		{
			"paths": [
				"M464.571 742.286l259.429-259.429q10.857-10.857 10.857-25.714t-10.857-25.714l-58.286-58.286q-10.857-10.857-25.714-10.857t-25.714 10.857l-175.429 175.429-175.429-175.429q-10.857-10.857-25.714-10.857t-25.714 10.857l-58.286 58.286q-10.857 10.857-10.857 25.714t10.857 25.714l259.429 259.429q10.857 10.857 25.714 10.857t25.714-10.857zM877.714 512q0 119.429-58.857 220.286t-159.714 159.714-220.286 58.857-220.286-58.857-159.714-159.714-58.857-220.286 58.857-220.286 159.714-159.714 220.286-58.857 220.286 58.857 159.714 159.714 58.857 220.286z"
			],
			"width": 877.7139282226562,
			"tags": [
				"chevron-circle-down"
			],
			"defaultCode": 61754,
			"grid": 14
		},
		{
			"paths": [
				"M519.429 797.143l58.286-58.286q10.857-10.857 10.857-25.714t-10.857-25.714l-175.429-175.429 175.429-175.429q10.857-10.857 10.857-25.714t-10.857-25.714l-58.286-58.286q-10.857-10.857-25.714-10.857t-25.714 10.857l-259.429 259.429q-10.857 10.857-10.857 25.714t10.857 25.714l259.429 259.429q10.857 10.857 25.714 10.857t25.714-10.857zM877.714 512q0 119.429-58.857 220.286t-159.714 159.714-220.286 58.857-220.286-58.857-159.714-159.714-58.857-220.286 58.857-220.286 159.714-159.714 220.286-58.857 220.286 58.857 159.714 159.714 58.857 220.286z"
			],
			"width": 877.7139282226562,
			"tags": [
				"chevron-circle-left"
			],
			"defaultCode": 61751,
			"grid": 14
		},
		{
			"paths": [
				"M409.714 797.143l259.429-259.429q10.857-10.857 10.857-25.714t-10.857-25.714l-259.429-259.429q-10.857-10.857-25.714-10.857t-25.714 10.857l-58.286 58.286q-10.857 10.857-10.857 25.714t10.857 25.714l175.429 175.429-175.429 175.429q-10.857 10.857-10.857 25.714t10.857 25.714l58.286 58.286q10.857 10.857 25.714 10.857t25.714-10.857zM877.714 512q0 119.429-58.857 220.286t-159.714 159.714-220.286 58.857-220.286-58.857-159.714-159.714-58.857-220.286 58.857-220.286 159.714-159.714 220.286-58.857 220.286 58.857 159.714 159.714 58.857 220.286z"
			],
			"width": 877.7139282226562,
			"tags": [
				"chevron-circle-right"
			],
			"defaultCode": 61752,
			"grid": 14
		},
		{
			"paths": [
				"M665.714 650.857l58.286-58.286q10.857-10.857 10.857-25.714t-10.857-25.714l-259.429-259.429q-10.857-10.857-25.714-10.857t-25.714 10.857l-259.429 259.429q-10.857 10.857-10.857 25.714t10.857 25.714l58.286 58.286q10.857 10.857 25.714 10.857t25.714-10.857l175.429-175.429 175.429 175.429q10.857 10.857 25.714 10.857t25.714-10.857zM877.714 512q0 119.429-58.857 220.286t-159.714 159.714-220.286 58.857-220.286-58.857-159.714-159.714-58.857-220.286 58.857-220.286 159.714-159.714 220.286-58.857 220.286 58.857 159.714 159.714 58.857 220.286z"
			],
			"width": 877.7139282226562,
			"tags": [
				"chevron-circle-up"
			],
			"defaultCode": 61753,
			"grid": 14
		},
		{
			"paths": [
				"M961.714 461.714l-424 423.429q-10.857 10.857-25.714 10.857t-25.714-10.857l-424-423.429q-10.857-10.857-10.857-26t10.857-26l94.857-94.286q10.857-10.857 25.714-10.857t25.714 10.857l303.429 303.429 303.429-303.429q10.857-10.857 25.714-10.857t25.714 10.857l94.857 94.286q10.857 10.857 10.857 26t-10.857 26z"
			],
			"width": 1023.9999237060547,
			"tags": [
				"chevron-down"
			],
			"defaultCode": 61560,
			"grid": 14
		},
		{
			"paths": [
				"M669.143 172l-303.429 303.429 303.429 303.429q10.857 10.857 10.857 25.714t-10.857 25.714l-94.857 94.857q-10.857 10.857-25.714 10.857t-25.714-10.857l-424-424q-10.857-10.857-10.857-25.714t10.857-25.714l424-424q10.857-10.857 25.714-10.857t25.714 10.857l94.857 94.857q10.857 10.857 10.857 25.714t-10.857 25.714z"
			],
			"width": 768.0010223388672,
			"tags": [
				"chevron-left"
			],
			"defaultCode": 61523,
			"grid": 14
		},
		{
			"paths": [
				"M632.571 501.143l-424 424q-10.857 10.857-25.714 10.857t-25.714-10.857l-94.857-94.857q-10.857-10.857-10.857-25.714t10.857-25.714l303.429-303.429-303.429-303.429q-10.857-10.857-10.857-25.714t10.857-25.714l94.857-94.857q10.857-10.857 25.714-10.857t25.714 10.857l424 424q10.857 10.857 10.857 25.714t-10.857 25.714z"
			],
			"width": 694.8569641113281,
			"tags": [
				"chevron-right"
			],
			"defaultCode": 61524,
			"grid": 14
		},
		{
			"paths": [
				"M961.714 760.571l-94.857 94.286q-10.857 10.857-25.714 10.857t-25.714-10.857l-303.429-303.429-303.429 303.429q-10.857 10.857-25.714 10.857t-25.714-10.857l-94.857-94.286q-10.857-10.857-10.857-26t10.857-26l424-423.429q10.857-10.857 25.714-10.857t25.714 10.857l424 423.429q10.857 10.857 10.857 26t-10.857 26z"
			],
			"width": 1023.9999694824219,
			"tags": [
				"chevron-up"
			],
			"defaultCode": 61559,
			"grid": 14
		},
		{
			"paths": [
				"M731.429 530.286q0-8-5.143-13.143t-13.143-5.143h-128v-201.143q0-7.429-5.429-12.857t-12.857-5.429h-109.714q-7.429 0-12.857 5.429t-5.429 12.857v201.143h-128q-7.429 0-12.857 5.429t-5.429 12.857q0 8 5.143 13.143l201.143 201.143q5.143 5.143 13.143 5.143t13.143-5.143l200.571-200.571q5.714-6.857 5.714-13.714zM1097.143 658.286q0 90.857-64.286 155.143t-155.143 64.286h-621.714q-105.714 0-180.857-75.143t-75.143-180.857q0-74.286 40-137.143t107.429-94.286q-1.143-17.143-1.143-24.571 0-121.143 85.714-206.857t206.857-85.714q89.143 0 163.143 49.714t107.714 132q40.571-35.429 94.857-35.429 60.571 0 103.429 42.857t42.857 103.429q0 43.429-23.429 78.857 74.286 17.714 122 77.429t47.714 136.286z"
			],
			"width": 1097.1429443359375,
			"tags": [
				"cloud-download"
			],
			"defaultCode": 61677,
			"grid": 14
		},
		{
			"paths": [
				"M731.429 493.714q0-8-5.143-13.143l-201.143-201.143q-5.143-5.143-13.143-5.143t-13.143 5.143l-200.571 200.571q-5.714 6.857-5.714 13.714 0 8 5.143 13.143t13.143 5.143h128v201.143q0 7.429 5.429 12.857t12.857 5.429h109.714q7.429 0 12.857-5.429t5.429-12.857v-201.143h128q7.429 0 12.857-5.429t5.429-12.857zM1097.143 658.286q0 90.857-64.286 155.143t-155.143 64.286h-621.714q-105.714 0-180.857-75.143t-75.143-180.857q0-74.286 40-137.143t107.429-94.286q-1.143-17.143-1.143-24.571 0-121.143 85.714-206.857t206.857-85.714q89.143 0 163.143 49.714t107.714 132q40.571-35.429 94.857-35.429 60.571 0 103.429 42.857t42.857 103.429q0 43.429-23.429 78.857 74.286 17.714 122 77.429t47.714 136.286z"
			],
			"width": 1097.1429443359375,
			"tags": [
				"cloud-upload"
			],
			"defaultCode": 61678,
			"grid": 14
		},
		{
			"paths": [
				"M438.857 548.571v256q0 14.857-10.857 25.714t-25.714 10.857-25.714-10.857l-82.286-82.286-189.714 189.714q-5.714 5.714-13.143 5.714t-13.143-5.714l-65.143-65.143q-5.714-5.714-5.714-13.143t5.714-13.143l189.714-189.714-82.286-82.286q-10.857-10.857-10.857-25.714t10.857-25.714 25.714-10.857h256q14.857 0 25.714 10.857t10.857 25.714zM870.286 164.571q0 7.429-5.714 13.143l-189.714 189.714 82.286 82.286q10.857 10.857 10.857 25.714t-10.857 25.714-25.714 10.857h-256q-14.857 0-25.714-10.857t-10.857-25.714v-256q0-14.857 10.857-25.714t25.714-10.857 25.714 10.857l82.286 82.286 189.714-189.714q5.714-5.714 13.143-5.714t13.143 5.714l65.143 65.143q5.714 5.714 5.714 13.143z"
			],
			"width": 877.7160587310791,
			"tags": [
				"compress"
			],
			"defaultCode": 61542,
			"grid": 14
		},
		{
			"paths": [
				"M731.429 768q0-14.857-10.857-25.714t-25.714-10.857-25.714 10.857-10.857 25.714 10.857 25.714 25.714 10.857 25.714-10.857 10.857-25.714zM877.714 768q0-14.857-10.857-25.714t-25.714-10.857-25.714 10.857-10.857 25.714 10.857 25.714 25.714 10.857 25.714-10.857 10.857-25.714zM950.857 640v182.857q0 22.857-16 38.857t-38.857 16h-841.143q-22.857 0-38.857-16t-16-38.857v-182.857q0-22.857 16-38.857t38.857-16h265.714l77.143 77.714q33.143 32 77.714 32t77.714-32l77.714-77.714h265.143q22.857 0 38.857 16t16 38.857zM765.143 314.857q9.714 23.429-8 40l-256 256q-10.286 10.857-25.714 10.857t-25.714-10.857l-256-256q-17.714-16.571-8-40 9.714-22.286 33.714-22.286h146.286v-256q0-14.857 10.857-25.714t25.714-10.857h146.286q14.857 0 25.714 10.857t10.857 25.714v256h146.286q24 0 33.714 22.286z"
			],
			"width": 950.8569869995117,
			"tags": [
				"download"
			],
			"defaultCode": 61465,
			"grid": 14
		},
		{
			"paths": [
				"M1024 676.571v109.714q0 7.429-5.429 12.857t-12.857 5.429h-786.286v109.714q0 7.429-5.429 12.857t-12.857 5.429q-6.857 0-13.714-5.714l-182.286-182.857q-5.143-5.143-5.143-12.571 0-8 5.143-13.143l182.857-182.857q5.143-5.143 13.143-5.143 7.429 0 12.857 5.429t5.429 12.857v109.714h786.286q7.429 0 12.857 5.429t5.429 12.857zM1024 365.714q0 8-5.143 13.143l-182.857 182.857q-5.143 5.143-13.143 5.143-7.429 0-12.857-5.429t-5.429-12.857v-109.714h-786.286q-7.429 0-12.857-5.429t-5.429-12.857v-109.714q0-7.429 5.429-12.857t12.857-5.429h786.286v-109.714q0-8 5.143-13.143t13.143-5.143q6.857 0 13.714 5.714l182.286 182.286q5.143 5.143 5.143 13.143z"
			],
			"width": 1023.9989223480225,
			"tags": [
				"exchange"
			],
			"defaultCode": 61676,
			"grid": 14
		},
		{
			"paths": [
				"M431.429 603.429q0 7.429-5.714 13.143l-189.714 189.714 82.286 82.286q10.857 10.857 10.857 25.714t-10.857 25.714-25.714 10.857h-256q-14.857 0-25.714-10.857t-10.857-25.714v-256q0-14.857 10.857-25.714t25.714-10.857 25.714 10.857l82.286 82.286 189.714-189.714q5.714-5.714 13.143-5.714t13.143 5.714l65.143 65.143q5.714 5.714 5.714 13.143zM877.714 109.714v256q0 14.857-10.857 25.714t-25.714 10.857-25.714-10.857l-82.286-82.286-189.714 189.714q-5.714 5.714-13.143 5.714t-13.143-5.714l-65.143-65.143q-5.714-5.714-5.714-13.143t5.714-13.143l189.714-189.714-82.286-82.286q-10.857-10.857-10.857-25.714t10.857-25.714 25.714-10.857h256q14.857 0 25.714 10.857t10.857 25.714z"
			],
			"width": 877.7159690856934,
			"tags": [
				"expand"
			],
			"defaultCode": 61541,
			"grid": 14
		},
		{
			"paths": [
				"M804.571 548.571q0-48-18.286-104.571t-36.571-110.857-18.286-95.429v-18.286h-365.714v18.286q0 20-6.857 38.571t-21.143 35.714-26.286 28.571-30.857 28q-5.143 4.571-8 6.857-46.286 41.143-82.857 64-12.571 8-38.857 21.714-1.714 0.571-12.857 6t-20.571 10.571-20.286 11.429-17.429 12.286-6.571 10.571q0 40.571 17.429 66t55.714 25.429q24.571 0 48.286-8.571t38.857-18.857 31.429-18.857 27.714-8.571v329.143q0 28.571 22 50.857t51.143 22.286q29.714 0 51.429-21.714t21.714-51.429v-189.143q26.286 20 58.857 20 39.429 0 68-30.286 18.286 10.286 39.429 10.286t42-10 30-27.143q13.714 2.286 32 2.286 48.571 0 72-27.714t23.429-77.429zM731.429 109.714q0-14.857-10.857-25.714t-25.714-10.857-25.714 10.857-10.857 25.714 10.857 25.714 25.714 10.857 25.714-10.857 10.857-25.714zM877.714 546.286q0 81.143-44.286 131.429t-124.286 49.714l-2.857-0.571q-43.429 34.857-101.714 34.857-12.571 0-24.571-1.714-30.857 17.143-68 21.143v96.571q0 60-43.429 103.143t-103.429 43.143q-58.857 0-102.286-43.429t-43.429-102.857v-213.714q-30.857 12.571-73.143 12.571-69.143 0-107.714-46.571t-38.571-118q0-21.714 10-39.714t28.286-31.429 36-23.143 41.143-21.143 35.429-18.857q31.429-20 73.714-57.143 1.714-1.143 9.714-8t12.286-10.857 12.286-11.714 12.857-13.714 10.286-12.857 8-13.429 2.571-12.286v-164.571q0-30.286 21.429-51.714t51.714-21.429h365.714q30.286 0 51.714 21.429t21.429 51.714v164.571q0 33.714 33.714 127.429 39.429 108.571 39.429 181.143z"
			],
			"width": 877.7129669189453,
			"tags": [
				"hand-o-down"
			],
			"defaultCode": 61607,
			"grid": 14
		},
		{
			"paths": [
				"M786.286 804.571h18.286v-365.714h-18.286q-20 0-38.571-6.857t-35.714-21.143-28.571-26.286-28-30.857q-1.143-1.714-2-2.571t-2.286-2.571-2.571-2.857q-41.143-46.286-64-82.857-8-12.571-21.714-38.857-0.571-1.714-6-12.857t-10.571-20.571-11.429-20.286-12.286-17.429-10.571-6.571q-40.571 0-66 17.429t-25.429 55.714q0 24.571 8.571 48.286t18.857 38.857 18.857 31.429 8.571 27.714h-329.143q-28.571 0-50.857 22t-22.286 51.143q0 29.714 21.714 51.429t51.429 21.714h189.143q-8.571 9.714-14.286 27.143t-5.714 31.714q0 39.429 30.286 68-10.286 18.286-10.286 39.429t10 42 27.143 30q-2.286 13.714-2.286 32 0 48.571 27.714 72t77.429 23.429q48 0 104.571-18.286t110.857-36.571 95.429-18.286zM950.857 768q0-14.857-10.857-25.714t-25.714-10.857-25.714 10.857-10.857 25.714 10.857 25.714 25.714 10.857 25.714-10.857 10.857-25.714zM1024 438.857v365.714q0 30.286-21.429 51.714t-51.714 21.429h-164.571q-33.714 0-127.429 33.714-108.571 39.429-181.143 39.429-81.143 0-131.429-44.286t-49.714-124.286l0.571-2.857q-34.857-43.429-34.857-101.714 0-12.571 1.714-24.571-18.857-32.571-21.143-68h-96.571q-60 0-103.143-43.429t-43.143-103.429q0-58.857 43.429-102.286t102.857-43.429h213.714q-12.571-34.286-12.571-73.143 0-69.714 46.571-108t118-38.286q21.714 0 39.714 10t31.429 28.286 23.143 36 21.143 41.143 18.857 35.429q20 31.429 57.143 73.714 1.143 1.714 8 9.714t10.857 12.286 11.714 12.286 13.714 12.857 12.857 10.286 13.429 8 12.286 2.571h164.571q30.286 0 51.714 21.429t21.429 51.714z"
			],
			"width": 1023.9989547729492,
			"tags": [
				"hand-o-left"
			],
			"defaultCode": 61605,
			"grid": 14
		},
		{
			"paths": [
				"M146.286 768q0-14.857-10.857-25.714t-25.714-10.857-25.714 10.857-10.857 25.714 10.857 25.714 25.714 10.857 25.714-10.857 10.857-25.714zM950.857 438.857q0-29.143-22.286-51.143t-50.857-22h-329.143q0-11.429 8.571-27.714t18.857-31.429 18.857-38.857 8.571-48.286q0-38.286-25.429-55.714t-66-17.429q-13.714 0-51.429 79.429-13.714 25.143-21.143 37.143-22.857 36.571-64 82.857-40.571 46.286-57.714 60.571-39.429 32.571-80 32.571h-18.286v365.714h18.286q41.143 0 95.429 18.286t110.571 36.571 102.571 18.286q108 0 108-95.429 0-14.857-2.857-32 17.143-9.143 27.143-30t10-42-10.286-39.429q30.286-28.571 30.286-68 0-14.286-5.714-31.714t-14.286-27.143h189.143q29.714 0 51.429-21.714t21.714-51.429zM1024 438.286q0 60-43.143 103.429t-103.143 43.429h-96.571q-2.286 35.429-21.143 68 1.714 12 1.714 24.571 0 57.714-34.286 101.714 0.571 79.429-48.571 125.429t-129.714 46q-76 0-184-39.429-93.714-33.714-127.429-33.714h-164.571q-30.286 0-51.714-21.429t-21.429-51.714v-365.714q0-30.286 21.429-51.714t51.714-21.429h164.571q5.714 0 12.286-2.571t13.429-8 12.857-10.286 13.714-12.857 11.714-12.286 10.857-12.286 8-9.714q37.143-42.286 57.143-73.714 7.429-12 18.857-35.429t21.143-41.143 23.143-36 31.429-28.286 39.714-10q71.429 0 118 38.286t46.571 108q0 38.857-12.571 73.143h213.714q59.429 0 102.857 43.429t43.429 102.286z"
			],
			"width": 1024.0000076293945,
			"tags": [
				"hand-o-right"
			],
			"defaultCode": 61604,
			"grid": 14
		},
		{
			"paths": [
				"M731.429 914.286q0-14.857-10.857-25.714t-25.714-10.857-25.714 10.857-10.857 25.714 10.857 25.714 25.714 10.857 25.714-10.857 10.857-25.714zM804.571 477.714q0-108-95.429-108-14.857 0-32 2.857-9.143-17.143-30-27.143t-42-10-39.429 10.286q-28.571-30.286-68-30.286-14.286 0-31.714 5.714t-27.143 14.286v-189.143q0-29.714-21.714-51.429t-51.429-21.714q-29.143 0-51.143 22.286t-22 50.857v329.143q-11.429 0-27.714-8.571t-31.429-18.857-38.857-18.857-48.286-8.571q-38.286 0-55.714 25.429t-17.429 66q0 13.714 79.429 51.429 25.143 13.714 37.143 21.143 36.571 22.857 82.857 64 46.286 40.571 60.571 57.714 32.571 39.429 32.571 80v18.286h365.714v-18.286q0-41.143 18.286-95.429t36.571-110.571 18.286-102.571zM877.714 474.857q0 76-39.429 184-33.714 93.714-33.714 127.429v164.571q0 30.286-21.429 51.714t-51.714 21.429h-365.714q-30.286 0-51.714-21.429t-21.429-51.714v-164.571q0-5.714-2.571-12.286t-8-13.429-10.286-12.857-12.857-13.714-12.286-11.714-12.286-10.857-9.714-8q-42.286-37.143-73.714-57.143-12-7.429-35.429-18.857t-41.143-21.143-36-23.143-28.286-31.429-10-39.714q0-71.429 38.286-118t108-46.571q38.857 0 73.143 12.571v-213.714q0-59.429 43.429-102.857t102.286-43.429q60 0 103.429 43.143t43.429 103.143v96.571q35.429 2.286 68 21.143 12-1.714 24.571-1.714 57.714 0 101.714 34.286 79.429-0.571 125.429 48.571t46 129.714z"
			],
			"width": 877.7139129638672,
			"tags": [
				"hand-o-up"
			],
			"defaultCode": 61606,
			"grid": 14
		},
		{
			"paths": [
				"M877.714 512q0 89.143-34.857 170.286t-93.714 140-140 93.714-170.286 34.857q-98.286 0-186.857-41.429t-150.857-116.857q-4-5.714-3.714-12.857t4.857-11.714l78.286-78.857q5.714-5.143 14.286-5.143 9.143 1.143 13.143 6.857 41.714 54.286 102.286 84t128.571 29.714q59.429 0 113.429-23.143t93.429-62.571 62.571-93.429 23.143-113.429-23.143-113.429-62.571-93.429-93.429-62.571-113.429-23.143q-56 0-107.429 20.286t-91.429 58l78.286 78.857q17.714 17.143 8 39.429-9.714 22.857-33.714 22.857h-256q-14.857 0-25.714-10.857t-10.857-25.714v-256q0-24 22.857-33.714 22.286-9.714 39.429 8l74.286 73.714q61.143-57.714 139.714-89.429t162.571-31.714q89.143 0 170.286 34.857t140 93.714 93.714 140 34.857 170.286zM512 347.429v256q0 8-5.143 13.143t-13.143 5.143h-182.857q-8 0-13.143-5.143t-5.143-13.143v-36.571q0-8 5.143-13.143t13.143-5.143h128v-201.143q0-8 5.143-13.143t13.143-5.143h36.571q8 0 13.143 5.143t5.143 13.143z"
			],
			"width": 877.7160301208496,
			"tags": [
				"history"
			],
			"defaultCode": 61914,
			"grid": 14
		},
		{
			"paths": [
				"M18.286 146.286h402.286q7.429 0 12.857 5.429t5.429 13.429v493.143h109.714q22.857 0 33.143 21.143t-5.143 39.429l-182.857 219.429q-10.286 12.571-28 12.571t-28-12.571l-182.857-219.429q-14.857-17.714-5.143-39.429 10.286-21.143 33.143-21.143h109.714v-365.714h-182.857q-8 0-14.286-6.286l-91.429-109.714q-7.429-8-2.286-19.429 5.143-10.857 16.571-10.857z"
			],
			"width": 588.5720386505127,
			"tags": [
				"level-down"
			],
			"defaultCode": 61769,
			"grid": 14
		},
		{
			"paths": [
				"M581.714 344.571q-10.286 21.143-33.143 21.143h-109.714v493.714q0 8-5.143 13.143t-13.143 5.143h-402.286q-12 0-16.571-10.286-4.571-11.429 2.286-20l91.429-109.714q5.143-6.286 14.286-6.286h182.857v-365.714h-109.714q-22.857 0-33.143-21.143-9.714-21.143 5.143-38.857l182.857-219.429q10.286-12.571 28-12.571t28 12.571l182.857 219.429q15.429 18.286 5.143 38.857z"
			],
			"width": 589.1439800262451,
			"tags": [
				"level-up"
			],
			"defaultCode": 61768,
			"grid": 14
		},
		{
			"paths": [
				"M437.143 742.286q4.571 10.857-2.857 20l-200 219.429q-5.714 5.714-13.143 5.714-8 0-13.714-5.714l-202.857-219.429q-7.429-9.143-2.857-20 5.143-10.857 16.571-10.857h128v-713.143q0-8 5.143-13.143t13.143-5.143h109.714q8 0 13.143 5.143t5.143 13.143v713.143h128q12 0 16.571 10.857z"
			],
			"width": 438.857027053833,
			"tags": [
				"long-arrow-down"
			],
			"defaultCode": 61813,
			"grid": 14
		},
		{
			"paths": [
				"M1024 457.143v109.714q0 8-5.143 13.143t-13.143 5.143h-713.143v128q0 12-10.857 16.571t-20-2.857l-219.429-200q-5.714-5.714-5.714-13.143 0-8 5.714-13.714l219.429-202.286q9.143-8 20-3.429 10.857 5.143 10.857 16.571v128h713.143q8 0 13.143 5.143t5.143 13.143z"
			],
			"width": 1060.5709915161133,
			"tags": [
				"long-arrow-left"
			],
			"defaultCode": 61815,
			"grid": 14
		},
		{
			"paths": [
				"M987.429 510.286q0 8-5.714 13.714l-219.429 202.286q-9.143 8-20 3.429-10.857-5.143-10.857-16.571v-128h-713.143q-8 0-13.143-5.143t-5.143-13.143v-109.714q0-8 5.143-13.143t13.143-5.143h713.143v-128q0-12 10.857-16.571t20 2.857l219.429 200q5.714 5.714 5.714 13.143z"
			],
			"width": 987.4290380477905,
			"tags": [
				"long-arrow-right"
			],
			"defaultCode": 61816,
			"grid": 14
		},
		{
			"paths": [
				"M437.143 281.714q-5.143 10.857-16.571 10.857h-128v713.143q0 8-5.143 13.143t-13.143 5.143h-109.714q-8 0-13.143-5.143t-5.143-13.143v-713.143h-128q-12 0-16.571-10.857t2.857-20l200-219.429q5.714-5.714 13.143-5.714 8 0 13.714 5.714l202.857 219.429q7.429 9.143 2.857 20z"
			],
			"width": 438.8590087890625,
			"tags": [
				"long-arrow-up"
			],
			"defaultCode": 61814,
			"grid": 14
		},
		{
			"paths": [
				"M1024 365.714q0 14.857-10.857 25.714l-292.571 292.571q-10.857 10.857-25.714 10.857t-25.714-10.857-10.857-25.714v-146.286h-128q-56 0-100.286 3.429t-88 12.286-76 24.286-60.286 39.714-45.714 57.714-27.714 79.143-10 103.429q0 31.429 2.857 70.286 0 3.429 1.429 13.429t1.429 15.143q0 8.571-4.857 14.286t-13.429 5.714q-9.143 0-16-9.714-4-5.143-7.429-12.571t-7.714-17.143-6-13.714q-72.571-162.857-72.571-257.714 0-113.714 30.286-190.286 92.571-230.286 500-230.286h128v-146.286q0-14.857 10.857-25.714t25.714-10.857 25.714 10.857l292.571 292.571q10.857 10.857 10.857 25.714z"
			],
			"width": 1024.0031433105469,
			"tags": [
				"mail-forward",
				"share"
			],
			"defaultCode": 61540,
			"grid": 14
		},
		{
			"paths": [
				"M1024 640q0 94.857-72.571 257.714-1.714 4-6 13.714t-7.714 17.143-7.429 12.571q-6.857 9.714-16 9.714-8.571 0-13.429-5.714t-4.857-14.286q0-5.143 1.429-15.143t1.429-13.429q2.857-38.857 2.857-70.286 0-57.714-10-103.429t-27.714-79.143-45.714-57.714-60.286-39.714-76-24.286-88-12.286-100.286-3.429h-128v146.286q0 14.857-10.857 25.714t-25.714 10.857-25.714-10.857l-292.571-292.571q-10.857-10.857-10.857-25.714t10.857-25.714l292.571-292.571q10.857-10.857 25.714-10.857t25.714 10.857 10.857 25.714v146.286h128q407.429 0 500 230.286 30.286 76.571 30.286 190.286z"
			],
			"width": 1024.0030403137207,
			"tags": [
				"mail-reply",
				"reply"
			],
			"defaultCode": 61714,
			"grid": 14
		},
		{
			"paths": [
				"M365.714 618.286v40q0 24-22.286 33.714-7.429 2.857-14.286 2.857-15.429 0-25.714-10.857l-292.571-292.571q-10.857-10.857-10.857-25.714t10.857-25.714l292.571-292.571q16.571-17.714 40-8 22.286 9.714 22.286 33.714v39.429l-226.857 227.429q-10.857 10.857-10.857 25.714t10.857 25.714zM1024 640q0 33.143-9.714 76.286t-22 78.857-27.429 71.429-23.143 51.714l-11.429 22.857q-4.571 9.714-16 9.714-3.429 0-5.143-0.571-14.286-4.571-13.143-19.429 24.571-228.571-60.571-322.857-36.571-40.571-97.429-63.143t-152.857-30v143.429q0 24-22.286 33.714-7.429 2.857-14.286 2.857-15.429 0-25.714-10.857l-292.571-292.571q-10.857-10.857-10.857-25.714t10.857-25.714l292.571-292.571q16.571-17.714 40-8 22.286 9.714 22.286 33.714v149.714q234.857 16 342.286 126.286 96.571 98.857 96.571 290.857z"
			],
			"width": 1023.999927520752,
			"tags": [
				"mail-reply-all",
				"reply-all"
			],
			"defaultCode": 61730,
			"grid": 14
		},
		{
			"paths": [
				"M380.571 274.857q-34.286 52.571-78.286 156-12.571-25.714-21.143-41.429t-23.143-36.286-29.143-32.286-36-20-46.571-8.286h-128q-8 0-13.143-5.143t-5.143-13.143v-109.714q0-8 5.143-13.143t13.143-5.143h128q142.857 0 234.286 128.571zM1024 731.429q0 8-5.143 13.143l-182.857 182.857q-5.143 5.143-13.143 5.143-7.429 0-12.857-5.429t-5.429-12.857v-109.714q-18.286 0-48.571 0.286t-46.286 0.571-41.714-0.571-40.571-2.857-36.571-6-36-10.571-33.143-16.286-33.714-22.857-31.429-30.571-32-39.714q33.714-53.143 77.714-156 12.571 25.714 21.143 41.429t23.143 36.286 29.143 32.286 36 20 46.571 8.286h146.286v-109.714q0-8 5.143-13.143t13.143-5.143q6.857 0 13.714 5.714l182.286 182.286q5.143 5.143 5.143 13.143zM1024 219.429q0 8-5.143 13.143l-182.857 182.857q-5.143 5.143-13.143 5.143-7.429 0-12.857-5.429t-5.429-12.857v-109.714h-146.286q-27.429 0-49.714 8.571t-39.429 25.714-29.143 35.143-25.714 44.286q-18.286 35.429-44.571 97.714-16.571 37.714-28.286 63.429t-30.857 60-36.571 57.143-42.286 47.429-51.429 39.143-60.857 24-73.143 9.429h-128q-8 0-13.143-5.143t-5.143-13.143v-109.714q0-8 5.143-13.143t13.143-5.143h128q27.429 0 49.714-8.571t39.429-25.714 29.143-35.143 25.714-44.286q18.286-35.429 44.571-97.714 16.571-37.714 28.286-63.429t30.857-60 36.571-57.143 42.286-47.429 51.429-39.143 60.857-24 73.143-9.429h146.286v-109.714q0-8 5.143-13.143t13.143-5.143q6.857 0 13.714 5.714l182.286 182.286q5.143 5.143 5.143 13.143z"
			],
			"width": 1023.9998998641968,
			"tags": [
				"random"
			],
			"defaultCode": 61556,
			"grid": 14
		},
		{
			"paths": [
				"M863.429 603.429q0 2.857-0.571 4-36.571 153.143-153.143 248.286t-273.143 95.143q-83.429 0-161.429-31.429t-139.143-89.714l-73.714 73.714q-10.857 10.857-25.714 10.857t-25.714-10.857-10.857-25.714v-256q0-14.857 10.857-25.714t25.714-10.857h256q14.857 0 25.714 10.857t10.857 25.714-10.857 25.714l-78.286 78.286q40.571 37.714 92 58.286t106.857 20.571q76.571 0 142.857-37.143t106.286-102.286q6.286-9.714 30.286-66.857 4.571-13.143 17.143-13.143h109.714q7.429 0 12.857 5.429t5.429 12.857zM877.714 146.286v256q0 14.857-10.857 25.714t-25.714 10.857h-256q-14.857 0-25.714-10.857t-10.857-25.714 10.857-25.714l78.857-78.857q-84.571-78.286-199.429-78.286-76.571 0-142.857 37.143t-106.286 102.286q-6.286 9.714-30.286 66.857-4.571 13.143-17.143 13.143h-113.714q-7.429 0-12.857-5.429t-5.429-12.857v-4q37.143-153.143 154.286-248.286t274.286-95.143q83.429 0 162.286 31.714t140 89.429l74.286-73.714q10.857-10.857 25.714-10.857t25.714 10.857 10.857 25.714z"
			],
			"width": 877.7150115966797,
			"tags": [
				"refresh"
			],
			"defaultCode": 61473,
			"grid": 14
		},
		{
			"paths": [
				"M877.714 146.286v256q0 14.857-10.857 25.714t-25.714 10.857h-256q-24 0-33.714-22.857-9.714-22.286 8-39.429l78.857-78.857q-84.571-78.286-199.429-78.286-59.429 0-113.429 23.143t-93.429 62.571-62.571 93.429-23.143 113.429 23.143 113.429 62.571 93.429 93.429 62.571 113.429 23.143q68 0 128.571-29.714t102.286-84q4-5.714 13.143-6.857 8 0 14.286 5.143l78.286 78.857q5.143 4.571 5.429 11.714t-4.286 12.857q-62.286 75.429-150.857 116.857t-186.857 41.429q-89.143 0-170.286-34.857t-140-93.714-93.714-140-34.857-170.286 34.857-170.286 93.714-140 140-93.714 170.286-34.857q84 0 162.571 31.714t139.714 89.429l74.286-73.714q16.571-17.714 40-8 22.286 9.714 22.286 33.714z"
			],
			"width": 877.7160339355469,
			"tags": [
				"repeat",
				"rotate-right"
			],
			"defaultCode": 61470,
			"grid": 14
		},
		{
			"paths": [
				"M731.429 859.429q0 7.429-5.429 12.857t-12.857 5.429h-548.571q-4.571 0-7.714-1.143t-5.143-4-3.143-4.571-1.714-6.571-0.571-6.571v-342.857h-109.714q-14.857 0-25.714-10.857t-10.857-25.714q0-13.714 8.571-23.429l182.857-219.429q10.857-12.571 28-12.571t28 12.571l182.857 219.429q8.571 9.714 8.571 23.429 0 14.857-10.857 25.714t-25.714 10.857h-109.714v219.429h329.143q9.143 0 14.286 6.286l91.429 109.714q4 6.286 4 12zM1097.143 621.714q0 13.714-8.571 23.429l-182.857 219.429q-11.429 13.143-28 13.143t-28-13.143l-182.857-219.429q-8.571-9.714-8.571-23.429 0-14.857 10.857-25.714t25.714-10.857h109.714v-219.429h-329.143q-9.143 0-14.286-6.857l-91.429-109.714q-4-5.143-4-11.429 0-7.429 5.429-12.857t12.857-5.429h548.571q4.571 0 7.714 1.143t5.143 4 3.143 4.571 1.714 6.571 0.571 6.571v342.857h109.714q14.857 0 25.714 10.857t10.857 25.714z"
			],
			"width": 1097.1450004577637,
			"tags": [
				"retweet"
			],
			"defaultCode": 61561,
			"grid": 14
		},
		{
			"paths": [
				"M877.714 512q0 89.143-34.857 170.286t-93.714 140-140 93.714-170.286 34.857q-98.286 0-186.857-41.429t-150.857-116.857q-4-5.714-3.714-12.857t4.857-11.714l78.286-78.857q5.714-5.143 14.286-5.143 9.143 1.143 13.143 6.857 41.714 54.286 102.286 84t128.571 29.714q59.429 0 113.429-23.143t93.429-62.571 62.571-93.429 23.143-113.429-23.143-113.429-62.571-93.429-93.429-62.571-113.429-23.143q-56 0-107.429 20.286t-91.429 58l78.286 78.857q17.714 17.143 8 39.429-9.714 22.857-33.714 22.857h-256q-14.857 0-25.714-10.857t-10.857-25.714v-256q0-24 22.857-33.714 22.286-9.714 39.429 8l74.286 73.714q61.143-57.714 139.714-89.429t162.571-31.714q89.143 0 170.286 34.857t140 93.714 93.714 140 34.857 170.286z"
			],
			"width": 877.7160301208496,
			"tags": [
				"rotate-left",
				"undo"
			],
			"defaultCode": 61666,
			"grid": 14
		},
		{
			"paths": [
				"M574.286 629.143l201.143-201.143q10.857-10.857 10.857-25.714t-10.857-25.714l-201.143-201.143q-17.143-17.714-39.429-8-22.857 9.714-22.857 33.714v91.429q-68 0-123.429 11.143t-92.857 29.143-65.143 45.143-43.714 54.571-25.429 62.286-12.286 63.714-2.857 63.143q0 103.429 95.429 230.857 5.714 6.857 14.286 6.857 4 0 7.429-1.714 12.571-5.143 10.857-18.857-25.143-202.286 35.429-270.286 26.286-29.714 74.286-43.143t128-13.429v91.429q0 24 22.857 33.714 6.857 2.857 13.714 2.857 14.857 0 25.714-10.857zM877.714 237.714v548.571q0 68-48.286 116.286t-116.286 48.286h-548.571q-68 0-116.286-48.286t-48.286-116.286v-548.571q0-68 48.286-116.286t116.286-48.286h548.571q68 0 116.286 48.286t48.286 116.286z"
			],
			"width": 877.7129821777344,
			"tags": [
				"share-square"
			],
			"defaultCode": 61773,
			"grid": 14
		},
		{
			"paths": [
				"M804.571 565.143v148q0 68-48.286 116.286t-116.286 48.286h-475.429q-68 0-116.286-48.286t-48.286-116.286v-475.429q0-68 48.286-116.286t116.286-48.286h145.714q7.429 0 12.857 5.429t5.429 12.857q0 15.429-14.857 18.286-44 14.857-76 34.286-5.714 2.286-9.143 2.286h-64q-37.714 0-64.571 26.857t-26.857 64.571v475.429q0 37.714 26.857 64.571t64.571 26.857h475.429q37.714 0 64.571-26.857t26.857-64.571v-122.286q0-10.857 10.286-16.571 16-7.429 30.857-21.143 9.143-9.143 20-4.571 12 5.143 12 16.571zM940 281.714l-219.429 219.429q-10.286 10.857-25.714 10.857-6.857 0-14.286-2.857-22.286-9.714-22.286-33.714v-109.714h-91.429q-184.571 0-250.286 74.857-68 78.286-42.286 270.286 1.714 13.143-11.429 19.429-4.571 1.143-6.857 1.143-9.143 0-14.857-7.429-5.714-8-12-17.714t-22.571-39.143-28.286-56.857-22-65.143-10-69.714q0-28 2-52t8-51.429 16-50.286 26.857-46.571 39.143-42.286 54-35.143 71.143-27.714 91.143-17.429 112.286-6.286h91.429v-109.714q0-24 22.286-33.714 7.429-2.857 14.286-2.857 14.857 0 25.714 10.857l219.429 219.429q10.857 10.857 10.857 25.714t-10.857 25.714z"
			],
			"width": 950.8549499511719,
			"tags": [
				"share-square-o"
			],
			"defaultCode": 61509,
			"grid": 14
		},
		{
			"paths": [
				"M676.571 512q0 14.857-10.857 25.714l-310.857 310.857q-10.857 10.857-25.714 10.857t-25.714-10.857-10.857-25.714v-164.571h-256q-14.857 0-25.714-10.857t-10.857-25.714v-219.429q0-14.857 10.857-25.714t25.714-10.857h256v-164.571q0-14.857 10.857-25.714t25.714-10.857 25.714 10.857l310.857 310.857q10.857 10.857 10.857 25.714zM877.714 310.857v402.286q0 68-48.286 116.286t-116.286 48.286h-182.857q-7.429 0-12.857-5.429t-5.429-12.857q0-2.286-0.571-11.429t-0.286-15.143 1.714-13.429 5.714-11.143 11.714-3.714h182.857q37.714 0 64.571-26.857t26.857-64.571v-402.286q0-37.714-26.857-64.571t-64.571-26.857h-178.286t-6.571-0.571-6.571-1.714-4.571-3.143-4-5.143-1.143-7.714q0-2.286-0.571-11.429t-0.286-15.143 1.714-13.429 5.714-11.143 11.714-3.714h182.857q68 0 116.286 48.286t48.286 116.286z"
			],
			"width": 877.7149925231934,
			"tags": [
				"sign-in"
			],
			"defaultCode": 61584,
			"grid": 14
		},
		{
			"paths": [
				"M365.714 822.857q0 2.286 0.571 11.429t0.286 15.143-1.714 13.429-5.714 11.143-11.714 3.714h-182.857q-68 0-116.286-48.286t-48.286-116.286v-402.286q0-68 48.286-116.286t116.286-48.286h182.857q7.429 0 12.857 5.429t5.429 12.857q0 2.286 0.571 11.429t0.286 15.143-1.714 13.429-5.714 11.143-11.714 3.714h-182.857q-37.714 0-64.571 26.857t-26.857 64.571v402.286q0 37.714 26.857 64.571t64.571 26.857h178.286t6.571 0.571 6.571 1.714 4.571 3.143 4 5.143 1.143 7.714zM896 512q0 14.857-10.857 25.714l-310.857 310.857q-10.857 10.857-25.714 10.857t-25.714-10.857-10.857-25.714v-164.571h-256q-14.857 0-25.714-10.857t-10.857-25.714v-219.429q0-14.857 10.857-25.714t25.714-10.857h256v-164.571q0-14.857 10.857-25.714t25.714-10.857 25.714 10.857l310.857 310.857q10.857 10.857 10.857 25.714z"
			],
			"width": 896.0000305175781,
			"tags": [
				"sign-out"
			],
			"defaultCode": 61579,
			"grid": 14
		},
		{
			"paths": [
				"M585.143 621.714q0 14.857-10.857 25.714l-256 256q-10.857 10.857-25.714 10.857t-25.714-10.857l-256-256q-10.857-10.857-10.857-25.714t10.857-25.714 25.714-10.857h512q14.857 0 25.714 10.857t10.857 25.714zM585.143 402.286q0 14.857-10.857 25.714t-25.714 10.857h-512q-14.857 0-25.714-10.857t-10.857-25.714 10.857-25.714l256-256q10.857-10.857 25.714-10.857t25.714 10.857l256 256q10.857 10.857 10.857 25.714z"
			],
			"width": 585.1440086364746,
			"tags": [
				"sort",
				"unsorted"
			],
			"defaultCode": 61660,
			"grid": 14
		},
		{
			"paths": [
				"M585.143 402.286q0 14.857-10.857 25.714t-25.714 10.857h-512q-14.857 0-25.714-10.857t-10.857-25.714 10.857-25.714l256-256q10.857-10.857 25.714-10.857t25.714 10.857l256 256q10.857 10.857 10.857 25.714z"
			],
			"width": 585.1440086364746,
			"tags": [
				"sort-asc",
				"sort-up"
			],
			"defaultCode": 61662,
			"grid": 14
		},
		{
			"paths": [
				"M585.143 621.714q0 14.857-10.857 25.714l-256 256q-10.857 10.857-25.714 10.857t-25.714-10.857l-256-256q-10.857-10.857-10.857-25.714t10.857-25.714 25.714-10.857h512q14.857 0 25.714 10.857t10.857 25.714z"
			],
			"width": 585.1440315246582,
			"tags": [
				"sort-desc",
				"sort-down"
			],
			"defaultCode": 61661,
			"grid": 14
		},
		{
			"paths": [
				"M731.429 841.143q0-14.857-10.857-25.714t-25.714-10.857-25.714 10.857-10.857 25.714 10.857 25.714 25.714 10.857 25.714-10.857 10.857-25.714zM877.714 841.143q0-14.857-10.857-25.714t-25.714-10.857-25.714 10.857-10.857 25.714 10.857 25.714 25.714 10.857 25.714-10.857 10.857-25.714zM950.857 713.143v182.857q0 22.857-16 38.857t-38.857 16h-841.143q-22.857 0-38.857-16t-16-38.857v-182.857q0-22.857 16-38.857t38.857-16h244q12 32 40.286 52.571t63.143 20.571h146.286q34.857 0 63.143-20.571t40.286-52.571h244q22.857 0 38.857 16t16 38.857zM765.143 342.857q-9.714 22.857-33.714 22.857h-146.286v256q0 14.857-10.857 25.714t-25.714 10.857h-146.286q-14.857 0-25.714-10.857t-10.857-25.714v-256h-146.286q-24 0-33.714-22.857-9.714-22.286 8-39.429l256-256q10.286-10.857 25.714-10.857t25.714 10.857l256 256q17.714 17.143 8 39.429z"
			],
			"width": 950.858024597168,
			"tags": [
				"upload"
			],
			"defaultCode": 61587,
			"grid": 14
		}
	],
	"colorThemes": [],
	"preferences": {
		"showGlyphs": true,
		"showCodes": true,
		"showQuickUse": true,
		"showQuickUse2": true,
		"showSVGs": true,
		"fontPref": {
			"prefix": "icon-",
			"metadata": {},
			"metrics": {
				"emSize": 1024,
				"baseline": 6.25,
				"whitespace": 50
			}
		},
		"imagePref": {
			"prefix": "icon-",
			"png": true,
			"useClassSelector": true,
			"color": 0,
			"bgColor": 16777215,
			"classSelector": ".icon"
		},
		"historySize": 100
	},
	"IcoMoonType": "icon-set"
}